setup.py
MosT/__init__.py
MosT/basetest.py
MosT/caseobject.py
MosT/database.py
MosT/datacontext.py
MosT/datamanager.py
MosT/log.py
MosT/requestmanager.py
MosT/testcontrol.py
MosT/testmethodmanager.py
MosT/universalconfig.py
MosT.egg-info/PKG-INFO
MosT.egg-info/SOURCES.txt
MosT.egg-info/dependency_links.txt
MosT.egg-info/top_level.txt
MosT.egg-info/zip-safe