Metadata-Version: 1.1
Name: MosT
Version: 0.12
Summary: auto test with interface
Home-page: UNKNOWN
Author: tangke
Author-email: 243556090@qq.com
License: UNKNOWN
Keywords: auto test
Platform: UNKNOWN
Classifier: License :: OSI Approved :: MIT License
Classifier: Programming Language :: Python
Classifier: Intended Audience :: Developers
Classifier: Operating System :: OS Independent
